infra_screenshot-0.1.6.dist-info/licenses/LICENSE
infra_screenshot-0.1.6.dist-info/licenses/NOTICE
screenshot/__init__.py
screenshot/_models_options.py
screenshot/_models_plans.py
screenshot/_models_results.py
screenshot/cli.py
screenshot/cli_config.py
screenshot/cli_shared.py
screenshot/cli_utils.py
screenshot/defaults.py
screenshot/launch_policy.py
screenshot/models.py
screenshot/playwright_runner.py
screenshot/py.typed
screenshot/selenium_runner.py
screenshot/service.py
screenshot/_internal/__init__.py
screenshot/_internal/resource_transformer.py
screenshot/_shared/__init__.py
screenshot/_shared/errors.py
screenshot/_shared/options_normalizer.py
screenshot/_shared/storage.py
screenshot/_shared/types.py
screenshot/_shared/url.py
screenshot/_shared/cli/__init__.py
screenshot/_shared/cli/arguments.py
screenshot/_shared/cli/normalizers.py
screenshot/_shared/cli/options.py
screenshot/_shared/cli/options_builders.py
screenshot/_shared/cli/options_validate.py
screenshot/_shared/cli/parser.py
screenshot/_shared/cli/schema.py
screenshot/_shared/cli/utils.py
screenshot/_shared/cli/validator.py
screenshot/config/cli_v1.json
infra_screenshot-0.1.6.dist-info/METADATA
infra_screenshot-0.1.6.dist-info/WHEEL
infra_screenshot-0.1.6.dist-info/entry_points.txt
infra_screenshot-0.1.6.dist-info/top_level.txt
infra_screenshot-0.1.6.dist-info/RECORD
