Metadata-Version: 2.4
Name: infra-screenshot
Version: 0.1.6
Summary: Generic screenshot capture utilities (models, services, CLI helpers).
Author: Screenshot Package maintainers
Maintainer: Screenshot Package maintainers
License-Expression: AGPL-3.0-or-later OR LicenseRef-Proprietary
Project-URL: Homepage, https://github.com/pj-ms/infra-screenshot
Project-URL: Repository, https://github.com/pj-ms/infra-screenshot
Project-URL: Issues, https://github.com/pj-ms/infra-screenshot/issues
Keywords: screenshot,playwright,selenium,web-automation,testing
Classifier: Development Status :: 3 - Alpha
Classifier: Intended Audience :: Developers
Classifier: Programming Language :: Python :: 3
Classifier: Programming Language :: Python :: 3.10
Classifier: Programming Language :: Python :: 3.11
Classifier: Programming Language :: Python :: 3.12
Classifier: Topic :: Software Development :: Testing
Classifier: Topic :: Software Development :: Libraries
Classifier: Typing :: Typed
Requires-Python: >=3.10
License-File: LICENSE
License-File: NOTICE
Requires-Dist: infra-core>=0.7.3
Requires-Dist: typing-extensions>=4.5; python_version < "3.11"
Provides-Extra: playwright
Requires-Dist: playwright>=1.44; extra == "playwright"
Provides-Extra: selenium
Requires-Dist: selenium>=4.17; extra == "selenium"
Provides-Extra: dev
Requires-Dist: pytest>=8.0; extra == "dev"
Requires-Dist: pytest-asyncio>=0.23; extra == "dev"
Requires-Dist: pytest-cov>=4.0; extra == "dev"
Requires-Dist: mypy>=1.13.0; extra == "dev"
Requires-Dist: ruff>=0.8.0; extra == "dev"
Requires-Dist: pre-commit>=4.0.0; extra == "dev"
Requires-Dist: bump-my-version>=0.26.0; extra == "dev"
Requires-Dist: twine>=5.0; extra == "dev"
Provides-Extra: experiment
Requires-Dist: numpy>=1.24; extra == "experiment"
Requires-Dist: Pillow>=10.0; extra == "experiment"
Requires-Dist: PyYAML>=6.0; extra == "experiment"
Dynamic: license-file
